klops/VERSION
klops/__init__.py
klops/__main__.py
klops/cli.py
klops/config.py
klops/__pycache__/__init__.cpython-39.pyc
klops/__pycache__/config.cpython-39.pyc
klops/deployment/__init__.py
klops/deployment/deployment.py
klops/deployment/exception.py
klops/deployment/__pycache__/__init__.cpython-39.pyc
klops/deployment/__pycache__/deployment.cpython-39.pyc
klops/deployment/__pycache__/exception.cpython-39.pyc
klops/deployment/auth/__init__.py
klops/deployment/auth/default.py
klops/deployment/auth/gke.py
klops/deployment/auth/schema.py
klops/deployment/auth/__pycache__/__init__.cpython-39.pyc
klops/deployment/auth/__pycache__/default.cpython-39.pyc
klops/deployment/auth/__pycache__/gke.cpython-39.pyc
klops/deployment/auth/__pycache__/schema.cpython-39.pyc
klops/experiment/__init__.py
klops/experiment/exception.py
klops/experiment/experiment.py
klops/experiment/__pycache__/__init__.cpython-39.pyc
klops/experiment/__pycache__/exception.cpython-39.pyc
klops/experiment/__pycache__/experiment.cpython-39.pyc
klops/experiment/runner/__init__.py
klops/experiment/runner/base.py
klops/experiment/runner/basic.py
klops/experiment/runner/gridsearch.py
klops/experiment/runner/hyperopt.py
klops/experiment/runner/__pycache__/__init__.cpython-39.pyc
klops/experiment/runner/__pycache__/base.cpython-39.pyc
klops/experiment/runner/__pycache__/basic.cpython-39.pyc
klops/experiment/runner/__pycache__/gridsearch.cpython-39.pyc
klops/experiment/runner/__pycache__/hyperopt.cpython-39.pyc
klops/templates/deployment_template.json
klops/versioning/__init__.py
klops/versioning/helper.py
klops/versioning/versioning.py
klops/versioning/__pycache__/__init__.cpython-39.pyc
klops/versioning/__pycache__/helper.cpython-39.pyc
klops/versioning/__pycache__/versioning.cpython-39.pyc
klops-0.0.4.dist-info/LICENSE
klops-0.0.4.dist-info/METADATA
klops-0.0.4.dist-info/WHEEL
klops-0.0.4.dist-info/entry_points.txt
klops-0.0.4.dist-info/top_level.txt
klops-0.0.4.dist-info/RECORD
