Metadata-Version: 2.1
Name: klops
Version: 0.0.4
Summary: Klops: Koin Machine Learning Ops
Home-page: https://gitlab-engineering.koinworks.com/data-team/klops/
Author: Koinworks Data Team
License-File: LICENSE
Requires-Dist: click
Requires-Dist: dvc
Requires-Dist: google-cloud
Requires-Dist: google-cloud-container
Requires-Dist: google-cloud-storage
Requires-Dist: google-auth
Requires-Dist: hyperopt
Requires-Dist: kubernetes
Requires-Dist: joblib
Requires-Dist: matplotlib
Requires-Dist: mlflow
Requires-Dist: scikit-learn
Requires-Dist: seldon-core
Requires-Dist: pandas
Requires-Dist: numpy
Requires-Dist: tqdm
Provides-Extra: test
Requires-Dist: pytest ; extra == 'test'
Requires-Dist: coverage ; extra == 'test'
Requires-Dist: flake8 ; extra == 'test'
Requires-Dist: black ; extra == 'test'
Requires-Dist: isort ; extra == 'test'
Requires-Dist: pytest-cov ; extra == 'test'
Requires-Dist: codecov ; extra == 'test'
Requires-Dist: mypy ; extra == 'test'
Requires-Dist: gitchangelog ; extra == 'test'
Requires-Dist: mkdocs ; extra == 'test'
